simptools/__init__.py
simptools/data/__init__.py
simptools/data/data.py
simptools/graph/__init__.py
simptools/graph/graphs.py
simptools/image/__init__.py
simptools/image/core.py
simptools/math/__init__.py
simptools/math/basic.py
simptools_nimit-0.1.3.dist-info/licenses/LICENSE
simptools_nimit-0.1.3.dist-info/METADATA
simptools_nimit-0.1.3.dist-info/WHEEL
simptools_nimit-0.1.3.dist-info/top_level.txt
simptools_nimit-0.1.3.dist-info/RECORD
