Metadata-Version: 2.4
Name: simptools-nimit
Version: 0.1.3
Summary: Simple, beginner-friendly Python utility library for math and image operations.
Author-email: Nimit Biswas <officialnimitbiswas@gmail.com>
License: MIT
Project-URL: Homepage, https://github.com/nimit-b/simptools
Requires-Python: >=3.8
License-File: LICENSE
Requires-Dist: opencv-python
Requires-Dist: matplotlib
Dynamic: license-file
